{"word":"Piperidge","priority":"N/A","meanings":[{"part_of_speech":"noun","definition":"(Archaic) A type of spiced gingerbread.","english_definition":"(Archaic) A type of spiced gingerbread.","examples":[{"sentence":"She bought a piece of piperidge at the market.","translation":"彼女は市場でパイペリッジを一切れ買った。"}],"collocations":[],"synonyms":["gingerbread"],"antonyms":[]}],"etymology":{"value":"Derived from 'pepperidge', referring to the spice used in the gingerbread.","priority":"N/A"},"pronunciation":{"ipa":"/ˈpɪpərɪdʒ/","syllables":"Pi-per-idge"},"inflection":{},"usage_notes":{},"common_mistakes":{},"related_words":{},"level_frequency":{},"readability_explanation":{},"example_sentences":[]}