{"word":"orthopsychiatry","priority":"★☆☆","meanings":[{"part_of_speech":"noun","definition":"矯正精神医学（特に児童・青少年の精神衛生と適応問題を扱う精神医学の一分野）","english_definition":"A branch of psychiatry concerned with mental health and behavioral adjustment, especially in children and adolescents, focusing on preventive and corrective measures.","examples":[{"sentence":"Orthopsychiatry emphasizes early intervention in childhood behavioral disorders.","translation":"矯正精神医学は児童期の行動障害への早期介入を重視する。"},{"sentence":"The orthopsychiatry clinic provides multidisciplinary approaches for at-risk youth.","translation":"その矯正精神医学クリニックはリスクを抱える青少年に対して学際的アプローチを提供している。"}],"collocations":["orthopsychiatry clinic (矯正精神医学クリニック)","orthopsychiatry approach (矯正精神医学的アプローチ)","child orthopsychiatry (児童矯正精神医学)"],"synonyms":["preventive psychiatry","child psychiatry","developmental psychiatry"],"antonyms":["adult psychiatry","forensic psychiatry"]}],"etymology":{"value":"ギリシャ語の「orthos（正しい、矯正する）」と「psychiatry（精神医学）」の合成語。1920年代にアメリカの精神科医William Healyによって提唱され、当初は非行少年の心理的矯正を主眼とした。","priority":"★☆☆"},"pronunciation":{"ipa":"/ˌɔːrθoʊsaɪˈkaɪətri/","syllables":"or-tho-psy-chi-a-try"},"usage_notes":{"explanation":"専門医学用語であり、一般会話ではほとんど使用されない。主に学術論文・児童心理臨床・矯正施設などの文脈で用いられる。従来の治療精神医学（therapeutic psychiatry）と対比され、予防的観点と社会適応を重視する点が特徴。","priority":"★☆☆"},"related_words":{"derivatives":["orthopsychiatric (形容詞: 矯正精神医学の)","orthopsychiatrist (名詞: 矯正精神医学専門医)"],"associated_terms":["child guidance (児童指導)","behavioral modification (行動修正)","developmental psychology (発達心理学)","juvenile delinquency (少年非行)","preventive mental health (予防精神保健)"],"priority":"★☆☆"},"level_frequency":{"CEFR":"Not applicable (専門用語)","frequency_google_ngram":"極めて低頻度 (Extremely low frequency)","priority":"★☆☆"},"example_sentences":[{"sentence":"The orthopsychiatry movement pioneered community-based interventions for youth mental health.","translation":"矯正精神医学運動は青少年の精神保健に対する地域ベースの介入を開拓した。","type":"noun","meaning_category":"専門分野"},{"sentence":"Her research bridges orthopsychiatry and educational psychology.","translation":"彼女の研究は矯正精神医学と教育心理学を架橋するものだ。","type":"noun","meaning_category":"学際的分野"}]}