{"word":"baccy","priority":"★☆☆","meanings":[{"part_of_speech":"noun","definition":"(informal, chiefly British) タバコ","english_definition":"(informal, chiefly British) tobacco.","examples":[{"sentence":"He rolled his own baccy.","translation":"彼は自分でタバコを巻いた。"},{"sentence":"Got any baccy on you?","translation":"タバコ持ってる？"}],"collocations":["roll-your-own baccy (手巻きタバコ)"],"synonyms":["tobacco","fag (UK slang)","cigarette","weed (slang)"],"antonyms":[]}],"etymology":{"value":"おそらく「tobacco」の短縮形または訛った形。","priority":"★★☆"},"pronunciation":{"ipa":"/ˈbæki/","syllables":"bac-cy"},"inflection":{"noun_plural":"baccies (まれ)"},"usage_notes":{"explanation":"「**baccy**」は、主にイギリス英語で使われるインフォーマルなタバコの呼び方です。やや古風な響きがあり、フォーマルな場面では使用されません。主に手巻きタバコを指すことが多いですが、一般的なタバコを指すこともあります。","priority":"★★☆"},"common_mistakes":{"examples":[{"incorrect":"✗ I bought a baccy of cigarettes.","correct":"✓ I bought a packet/pack of cigarettes. / ✓ I bought some baccy.","note":"「baccy」は不可算名詞として使われることが多いです。可算名詞として使う場合は、具体的な量を表す言葉（例：a pouch of baccy）を伴います。"},{"incorrect":"✗ She is addicted to baccies.","correct":"✓ She is addicted to baccy.","note":"複数形「baccies」は非常にまれです。通常は単数形で「タバコ」全般を指します。"}],"priority":"★★☆"},"related_words":{"derivatives":[],"idioms_phrases":[],"priority":"★☆☆"},"level_frequency":{"CEFR":"B2 (イギリス英語話者との会話で理解できるレベル)","frequency_google_ngram":"低頻度 (Low frequency) - 主にイギリス英語圏で使用される。","priority":"★☆☆"},"readability_explanation":{"level":"C1","text":"「**baccy**」は、主にイギリス英語で使われるタバコのくだけた言い方です。フォーマルな場面では使いませんが、親しい間柄や日常会話で使われることがあります。イギリス英語の小説や映画などで見かけることがあります。アメリカ英語ではあまり使われません。"},"example_sentences":[{"sentence":"He always carries a pouch of **baccy** with him.","translation":"彼はいつもタバコの小袋を持ち歩いている。","type":"noun","meaning_category":"タバコ"},{"sentence":"Fancy a bit of **baccy**?","translation":"タバコでもどう？","type":"noun","meaning_category":"タバコ"}]}