{"word":"interdetto","priority":"N/A","meanings":[{"part_of_speech":"noun","definition":"(イタリア語) 禁止、禁令、差し止め","english_definition":"(Italian) prohibition, ban, interdiction","examples":[{"sentence":"L'interdetto di fumo nei locali pubblici è una legge importante.","translation":"公共の場での喫煙禁止は重要な法律です。"}],"collocations":[],"synonyms":["divieto","proibizione"],"antonyms":["permesso","autorizzazione"]},{"part_of_speech":"adjective","definition":"(イタリア語) 禁止された、差し止められた","english_definition":"(Italian) prohibited, banned, interdicted","examples":[{"sentence":"L'area è interdetta al pubblico per motivi di sicurezza.","translation":"その地域は安全上の理由で一般公開が禁止されています。"}],"collocations":[],"synonyms":["proibito","vietato"],"antonyms":["permesso","autorizzato"]}],"etymology":{"value":"ラテン語の「interdictus」（禁止された）に由来。動詞「interdicere」（禁止する）の過去分詞。","priority":"N/A"},"pronunciation":{"ipa":"/interˈdɛtto/","syllables":"in-ter-det-to"},"inflection":{"noun_plural":"interdetti","adjective_forms":{"masculine_singular":"interdetto","feminine_singular":"interdetta","masculine_plural":"interdetti","feminine_plural":"interdette"}},"usage_notes":{"explanation":"イタリア語の単語で、法的な禁止や宗教的な禁令を意味することがあります。法律や規則によって禁止されている状態を指す場合や、特定の場所への立ち入りが禁止されている状況などを表します。","priority":"N/A"},"common_mistakes":{"examples":[],"priority":"N/A"},"related_words":{"derivatives":["interdire (動詞: 禁止する)"],"priority":"N/A"},"level_frequency":{"CEFR":"N/A","frequency_google_ngram":"Low","priority":"N/A"},"readability_explanation":{"level":"N/A","text":"イタリア語の単語であるため、イタリア語学習者向けの説明となります。"},"example_sentences":[{"sentence":"Il giudice ha emesso un interdetto contro la costruzione.","translation":"裁判官は建設に対する差し止め命令を出した。","type":"noun","meaning_category":"禁止"},{"sentence":"L'accesso alla spiaggia è interdetto durante la notte.","translation":"夜間はビーチへのアクセスは禁止されています。","type":"adjective","meaning_category":"禁止された"}]}