{"word":"subgeometrical","priority":"☆☆☆","meanings":[{"part_of_speech":"adjective","definition":"幾何学的なものより小さい、または幾何学の範囲を下回る","english_definition":"Smaller than geometrical; pertaining to something below the scope or scale of geometry.","examples":[{"sentence":"The particles exhibited subgeometrical dimensions.","translation":"その粒子は、幾何学的な寸法を下回る大きさを示した。"},{"sentence":"Subgeometrical analysis is needed to understand the structure.","translation":"その構造を理解するには、幾何学の範囲を下回る分析が必要です。"}],"collocations":["subgeometrical dimensions","subgeometrical analysis","subgeometrical scale"],"synonyms":["infinitesimal","microscopic","ultramicroscopic"],"antonyms":["geometrical","macroscopic"]}],"etymology":{"value":"\"sub-\" (下) + \"geometrical\" (幾何学的な)","priority":"★★★"},"pronunciation":{"ipa":"/sʌbˌdʒiːəˈmɛtrɪkəl/","syllables":"sub-ge-o-met-ri-cal"},"inflection":{"notes":"adjective"},"usage_notes":{"explanation":"The term \"subgeometrical\" is used to describe something that is smaller or of a scale that is below what is normally considered within the scope of geometry. It's often used in scientific or technical contexts.","priority":"★★☆"},"common_mistakes":{"examples":[],"priority":"☆☆☆"},"related_words":{"derivatives":["geometry","geometrical"],"phrasal_verbs":[]},"level_frequency":{"CEFR":"N/A","frequency_google_ngram":"Low","priority":"☆☆☆"},"readability_explanation":{"level":"C2","text":"The word \"subgeometrical\" is a technical term used in scientific or mathematical contexts to describe something smaller than or below the scale of what is typically studied in geometry. Understanding requires familiarity with geometry and the prefix \"sub-\", meaning \"below\" or \"smaller than.\""},"example_sentences":[{"sentence":"The study focused on the subgeometrical properties of the material.","translation":"その研究は、その材料の幾何学的な範囲を下回る特性に焦点を当てていた。","type":"adjective","meaning_category":"サイズが幾何学的な範囲を下回る"},{"sentence":"A subgeometrical approach was necessary to model the interactions.","translation":"その相互作用をモデル化するには、幾何学の範囲を下回るアプローチが必要だった。","type":"adjective","meaning_category":"幾何学の範囲を下回る"}]}