{"word":"dryland","priority":"★☆☆","meanings":[{"part_of_speech":"noun","definition":"乾燥地、乾燥地帯","english_definition":"an area of land with a relatively dry climate, especially one used for farming without irrigation.","examples":[{"sentence":"Dryland farming is challenging due to the limited rainfall.","translation":"降雨量が限られているため、乾燥地農業は困難です。"},{"sentence":"Many dryland regions are facing desertification.","translation":"多くの乾燥地帯が砂漠化に直面しています。"},{"sentence":"The government is promoting sustainable dryland management practices.","translation":"政府は持続可能な乾燥地管理慣習を推進しています。"}],"collocations":["dryland farming (乾燥地農業)","dryland agriculture (乾燥地農業)","dryland ecosystem (乾燥地生態系)","dryland management (乾燥地管理)","dryland region (乾燥地帯)","dryland area (乾燥地帯)"],"synonyms":["arid land","semi-arid land","non-irrigated land"],"antonyms":["wetland","irrigated land"]},{"part_of_speech":"adjective","definition":"乾燥地の、乾燥地性の","english_definition":"relating to or characteristic of dryland.","examples":[{"sentence":"Dryland ecosystems are particularly vulnerable to climate change.","translation":"乾燥地生態系は気候変動に対して特に脆弱です。"},{"sentence":"Dryland crops are adapted to survive with minimal water.","translation":"乾燥地作物は最小限の水で生き残るように適応しています。"}],"collocations":["dryland ecosystem (乾燥地生態系)","dryland crops (乾燥地作物)","dryland species (乾燥地種)","dryland environment (乾燥地環境)"],"synonyms":["arid","semi-arid"],"antonyms":["wet","irrigated"]}],"etymology":{"value":"'Dry' (乾燥した) + 'land' (土地) の組み合わせ。文字通り「乾燥した土地」を意味する。","priority":"★★★"},"pronunciation":{"ipa":"/ˈdraɪˌlænd/","syllables":"dry-land"},"inflection":{"noun_plural":"drylands"},"usage_notes":{"explanation":"'Dryland' は、降水量が少なく、灌漑なしで農業を行うことが難しい地域を指します。 この用語は、地理学、農業、環境科学などの分野でよく使用されます。 乾燥地は、世界の陸地の大部分を占めており、多くの人々の生活を支えています。","priority":"★★☆"},"common_mistakes":{"examples":[{"incorrect":"✗ The dryland is very fertile.","correct":"✓ The dryland soil is often less fertile due to lack of water and nutrients.","note":"乾燥地は一般的に肥沃ではありません。"},{"incorrect":"✗ Dryland requires a lot of irrigation.","correct":"✓ Dryland farming relies on rainfall rather than irrigation.","note":"乾燥地農業は灌漑ではなく、降雨に依存します。"}],"priority":"★★☆"},"related_words":{"derivatives":["drylander (乾燥地居住者)"],"phrasal_verbs":[],"related_terms":["desertification (砂漠化)","aridity (乾燥)","xerophyte (乾燥植物)"],"priority":"★★☆"},"level_frequency":{"CEFR":"B2","frequency_google_ngram":"比較的低い (Relatively low)","priority":"★☆☆"},"readability_explanation":{"level":"B2","text":"「**dryland**」は、雨が少ない地域を指す専門用語です。農業や環境問題について議論する際に使われることが多いです。この単語を理解することで、水資源が限られた地域での生活や農業に関するニュース記事や学術論文をより深く理解することができます。専門的な文脈で使われることが多いので、日常会話ではあまり使いません。"},"example_sentences":[{"sentence":"Sustainable farming practices are crucial for preserving **dryland** ecosystems.","translation":"持続可能な農業慣行は、乾燥地生態系を保全するために不可欠です。","type":"noun","meaning_category":"乾燥地帯"},{"sentence":"**Dryland** agriculture faces unique challenges due to unpredictable rainfall patterns.","translation":"乾燥地農業は、予測不可能な降雨パターンにより、特有の課題に直面しています。","type":"adjective","meaning_category":"乾燥地の"},{"sentence":"Many communities in **drylands** depend on livestock for their livelihoods.","translation":"乾燥地帯の多くのコミュニティは、生活のために家畜に依存しています。","type":"noun","meaning_category":"乾燥地帯 (複数形)"}]}