{"word":"Mooress","priority":"★☆☆","meanings":[{"part_of_speech":"noun","definition":"A female Moor.","english_definition":"A female Moor.","examples":[{"sentence":"The Mooress was known for her beauty and wisdom.","translation":"そのムーアレスは、美しさと知恵で知られていました。"}],"collocations":[],"synonyms":["Moorish woman"],"antonyms":[]}],"etymology":{"value":"Derived from \"Moor\" with the feminine suffix \"-ess\".","priority":"★★☆"},"pronunciation":{"ipa":"/ˈmuːrɛs/","syllables":"moo-ress"},"inflection":{"noun_plural":"Mooresses"},"usage_notes":{"explanation":"This term is primarily historical and may be considered outdated or even offensive in some contexts due to its association with colonialism and historical power dynamics. It is best used with caution and awareness of its historical baggage.","priority":"★★☆"},"common_mistakes":{"examples":[],"priority":"★☆☆"},"related_words":{"derivatives":["Moor","Moorish"],"phrases":[]},"level_frequency":{"CEFR":"N/A","frequency_google_ngram":"Low","priority":"★☆☆"},"readability_explanation":{"level":"C2","text":"The word 'Mooress' refers to a female Moor. The term itself is not frequently used in modern English and carries historical connotations related to the Moorish people, who historically inhabited regions of North Africa and Iberia. Due to its historical context and potential for misinterpretation, it is advisable to use this term with caution."},"example_sentences":[{"sentence":"The painting depicted a Mooress in traditional attire.","translation":"その絵は、伝統的な衣装を身に着けたムーアレスを描いていました。","type":"noun","meaning_category":"female Moor"}]}