{"word":"attenuato","priority":"☆☆☆","meanings":[{"part_of_speech":"adverb","definition":"(音楽)だんだん弱く (イタリア語の音楽用語)","english_definition":"(music) gradually softer; dying away (Italian musical term)","examples":[{"sentence":"The score indicates 'attenuato' at the end of the phrase.","translation":"楽譜には、フレーズの終わりに「attenuato」と指示されている。"}],"collocations":["attenuato poco a poco (少しずつだんだん弱く)"],"synonyms":["diminuendo","morendo","smorzando"],"antonyms":["crescendo"]},{"part_of_speech":"adjective","definition":"(音楽)だんだん弱くなった (イタリア語の音楽用語)","english_definition":"(music) attenuated; having become gradually softer (Italian musical term)","examples":[{"sentence":"The final note should be played in an attenuato manner.","translation":"最後の音は、だんだん弱くなるように演奏されるべきだ。"}],"collocations":[],"synonyms":["diminished","faded"],"antonyms":["increased","strengthened"]}],"etymology":{"value":"イタリア語の「attenuare」（弱める、薄める）の過去分詞形「attenuato」に由来。ラテン語の「attenuare」（薄くする、細くする）から派生。","priority":"★★☆"},"pronunciation":{"ipa":"/at.te.nwaː.to/","syllables":"at-te-nua-to"},"inflection":{"notes":"イタリア語由来の単語のため、英語の文法的な屈折は通常適用されません。"},"usage_notes":{"explanation":"「**attenuato**」は主に音楽の楽譜で使われるイタリア語の用語で、「だんだん弱く」という意味を表します。演奏者に、その部分を徐々に音量を下げて演奏するように指示します。より一般的な音楽用語である「diminuendo」や「morendo」、「smorzando」とほぼ同義ですが、「attenuato」は特に消え入るような、弱々しい終わり方を指示するニュアンスが強い場合があります。英語の文章では、音楽の文脈以外ではほとんど使用されません。","priority":"★★★"},"common_mistakes":{"examples":[{"incorrect":"✗ The light was attenuato.","correct":"✓ The light was attenuated.","note":"音楽用語以外で「弱められた」「減衰された」という意味で使う場合は、英語の単語「attenuated」を使用します。"},{"incorrect":"✗ He spoke attenuato.","correct":"✓ He spoke softly.","note":"「弱々しく話した」という意味で使う場合は、より一般的な英語の副詞「softly」を使用します。"}],"priority":"★★☆"},"related_words":{"derivatives":["attenuate (動詞: 弱める、減衰させる)","attenuation (名詞: 減衰、弱化)"],"idioms_phrases":[],"priority":"★★☆"},"level_frequency":{"CEFR":"N/A (音楽専門用語)","frequency_google_ngram":"非常に低頻度 (Very low frequency) - 音楽関係の文献以外ではほとんど見られない。","priority":"★☆☆"},"readability_explanation":{"level":"C2","text":"「**Attenuato**」は、主に音楽の分野で使用されるイタリア語の専門用語です。楽譜上で、演奏者に対して徐々に音量を下げて、音楽が消え入るように終わらせることを指示するために用いられます。音楽理論や演奏に関する高度な知識を持つ読者を対象とした文章でのみ使用されるため、一般的な読解力レベルの評価は適用されません。音楽を専門とする人以外には馴染みのない単語です。"},"example_sentences":[{"sentence":"The composer marked the final bars 'attenuato'.","translation":"作曲家は最後の小節に「attenuato」と記した。","type":"adverb","meaning_category":"だんだん弱く"},{"sentence":"Play the passage with an attenuato effect.","translation":"その箇所をだんだん弱くなるように演奏しなさい。","type":"adjective","meaning_category":"だんだん弱くなった"}]}