{"word":"sole-source","priority":"★★★","meanings":[{"part_of_speech":"adjective","definition":"(ビジネス)単独供給の、唯一の供給源からの","english_definition":"(business) obtained from only one supplier; coming from a single source.","examples":[{"sentence":"The company decided to sole-source the parts from a local manufacturer.","translation":"その会社は部品を地元の製造業者から単独供給することに決定した。"},{"sentence":"A sole-source contract was awarded to the company due to their unique expertise.","translation":"その会社は、独自の専門知識により単独供給契約を授与された。"},{"sentence":"We are considering a sole-source agreement to ensure consistent quality.","translation":"一貫した品質を確保するために、単独供給契約を検討しています。"}],"collocations":["sole-source contract (単独供給契約)","sole-source supplier (単独供給業者)","sole-source procurement (単独供給調達)","sole-source agreement (単独供給協定)"],"synonyms":["single-source","exclusive source"],"antonyms":["multi-source","competitive bidding"]},{"part_of_speech":"verb","definition":"(ビジネス)単独供給する、唯一の供給源から調達する","english_definition":"(business) to obtain something from only one supplier.","examples":[{"sentence":"We sole-source our software from that vendor.","translation":"当社はそのベンダーからソフトウェアを単独供給しています。"},{"sentence":"The government often sole-sources specialized equipment.","translation":"政府は特殊な機器を単独供給することがよくあります。"}],"collocations":["sole-source something from someone (～を～から単独供給する)"],"synonyms":["single-source"],"antonyms":["multi-source","competitively bid"]}],"etymology":{"value":"「sole」（唯一の）と「source」（源）の組み合わせ。ビジネスや調達の文脈で、複数の供給元からではなく、特定の製品やサービスを一つの供給元からのみ得ることを指す。","priority":"★★☆"},"pronunciation":{"ipa":"/ˌsoʊl ˈsɔːrs/","syllables":"sole-source"},"inflection":{"notes":"動詞としては、通常の動詞の活用に従います。"},"usage_notes":{"explanation":"「**sole-source**」は、主にビジネスや調達の分野で使用される用語です。競争入札を行わず、特定の製品やサービスを唯一の供給元から調達することを指します。これは、その供給元が独自の技術や専門知識を持っている場合、緊急のニーズがある場合、または他の供給元が存在しない場合に正当化されることがあります。ただし、透明性やコスト効率の観点から、単独供給は慎重に検討されるべきです。","priority":"★★★"},"common_mistakes":{"examples":[{"incorrect":"✗ We are sole source the parts.","correct":"✓ We sole-source the parts.","note":"動詞として使用する場合、ハイフンなしで `sole-source` と書きます。また、主語と動詞の一致に注意してください。"},{"incorrect":"✗ It's a sole source contract.","correct":"✓ It's a sole-source contract.","note":"形容詞として使用する場合、ハイフンで繋ぎます。"}],"priority":"★★☆"},"related_words":{"derivatives":["sole-sourcing (名詞: 単独供給)"],"phrases":["sole-source justification (単独供給の正当化)","sole-source basis (単独供給の根拠)"],"priority":"★★☆"},"level_frequency":{"CEFR":"C1-C2 (専門的なビジネス語彙)","frequency_google_ngram":"比較的低頻度 (Relatively low frequency) - 特定の業界や分野でのみ頻繁に使用される。","priority":"★☆☆"},"readability_explanation":{"level":"C1","text":"「**sole-source**」は、ビジネスや調達の世界で使われる専門用語で、特定の製品やサービスを、競争入札を行わずに、たった一つの会社からだけ購入することを意味します。これは、その会社が特別な技術を持っていたり、すぐに必要なものがあったりする場合に行われます。しかし、他の会社と比べて価格が高くなる可能性もあるので、よく考えてから決める必要があります。"},"example_sentences":[{"sentence":"Due to the urgency, we had to **sole-source** the equipment.","translation":"緊急性のため、その機器を単独供給する必要がありました。","type":"verb","meaning_category":"単独供給する"},{"sentence":"The **sole-source** agreement allowed them to maintain control over the technology.","translation":"単独供給契約により、彼らは技術の管理を維持することができた。","type":"adjective","meaning_category":"単独供給の"},{"sentence":"The company defended its decision to **sole-source** the contract.","translation":"その会社は、契約を単独供給するという決定を擁護した。","type":"verb","meaning_category":"単独供給する"},{"sentence":"A **sole-source** justification was required to proceed with the purchase.","translation":"購入を進めるには、単独供給の正当化が必要でした。","type":"adjective","meaning_category":"単独供給の"}]}