{"word":"Polysemie","priority":"☆☆☆","meanings":[{"part_of_speech":"noun","definition":"多義性（たぎせい）: 一つの語が複数の意味を持つこと。","english_definition":"Polysemy: The coexistence of many possible meanings for a word or phrase.","examples":[{"sentence":"「頭」という言葉は、身体の一部、組織の長、物事の始まりなど、多義性を持つ。","translation":"The word \"head\" has polysemy, referring to a body part, the leader of an organization, or the beginning of something."},{"sentence":"多義性は、言語の柔軟性と表現力を高める。","translation":"Polysemy enhances the flexibility and expressiveness of language."}],"collocations":["語彙的（ごい-てき）多義性 (lexical polysemy)","構造的（こうぞう-てき）多義性 (structural polysemy)"],"synonyms":["多義語（たぎご）","多意性（たいせい）"],"antonyms":["同義性（どうぎせい）","単義性（たんぎせい）"]}],"etymology":{"value":"ギリシャ語の「polys」(多くの)と「sema」(意味)に由来する。","priority":"★★★"},"pronunciation":{"ipa":"/polizemiː/","syllables":"po-ly-se-mie"},"inflection":{"noun_plural":"Polysemien"},"usage_notes":{"explanation":"Polysemieは、言語学において、一つの単語が複数の関連する意味を持つ現象を指します。これは同音異義語（Homonymie）とは異なり、Polysemieの場合は意味の間に関連性があります。","priority":"★★★"},"common_mistakes":{"examples":[{"incorrect":"Die Homonymie ist ein Beispiel für Polysemie.","correct":"Die Polysemie ist ein Beispiel für Mehrdeutigkeit.","note":"Homonymie（同音異義語）はPolysemie（多義性）の例ではありません。Polysemieは意味の関連性がある場合に適用されます。"}],"priority":"★★☆"},"related_words":{"derivatives":["polysem (形容詞: 多義的な)"],"phrasal_verbs":[]},"level_frequency":{"CEFR":"C2","frequency_google_ngram":"低頻度","priority":"★☆☆"},"readability_explanation":{"level":"C1","text":"Polysemieは、一つの単語が複数の意味を持つことを指す専門用語です。言語学や意味論の文脈でよく使用されます。"},"example_sentences":[{"sentence":"Die Polysemie des Wortes 'Bank' kann zu Missverständnissen führen.","translation":"「Bank（銀行/ベンチ）」という単語の多義性は誤解を招く可能性があります。","type":"example","meaning_category":"多義性の例"},{"sentence":"Die Linguistik untersucht die Polysemie von Wörtern.","translation":"言語学は単語の多義性を研究します。","type":"example","meaning_category":"言語学における多義性"}]}