{"word":"NKS","priority":"☆☆☆","meanings":[{"part_of_speech":"noun","definition":"(略語)日本経済新聞社の略称 (Nikkei Keizai Shimbun)","english_definition":"(abbreviation) Abbreviation for Nikkei Keizai Shimbun (The Nikkei).","examples":[{"sentence":"NKSは日本の主要な経済新聞です。","translation":"NKS is a major economic newspaper in Japan."}],"collocations":["NKSの記事 (NKS article)","NKSの報道 (NKS coverage)","NKSを読む (read NKS)"],"synonyms":["日経","日本経済新聞"],"antonyms":[]}],"etymology":{"value":"日本経済新聞社のローマ字表記、Nikkei Keizai Shimbunの頭文字から。","priority":"★★★"},"pronunciation":{"ipa":"/ɛn keɪ ɛs/","syllables":"en-kei-es"},"inflection":{"notes":"名詞なので、複数形はありません。"},"usage_notes":{"explanation":"「NKS」は、主にビジネスや経済の分野で、日本経済新聞社を指す略語として使われます。一般の会話では「日経」という言葉がより一般的です。","priority":"★★★"},"common_mistakes":{"examples":[{"incorrect":"✗ 私はNKSを読みます。","correct":"✓ 私は日経を読みます。","note":"一般の会話では「日経」を使う方が自然です。"}],"priority":"★★☆"},"related_words":{"derivatives":["日経 (Nikkei)","日本経済新聞 (Nikkei Keizai Shimbun)"],"priority":"★★★"},"level_frequency":{"CEFR":"N/A","frequency_google_ngram":"低頻度 (Low frequency)","priority":"★☆☆"},"readability_explanation":{"level":"N/A","text":"「NKS」は日本経済新聞社の略称であり、ビジネスや経済の専門家以外にはあまり馴染みがないかもしれません。一般的な会話では「日経」という言葉を使う方が適切です。"},"example_sentences":[{"sentence":"NKSの記事によると、日本の経済は回復傾向にあるとのことです。","translation":"According to an NKS article, the Japanese economy is on a recovery trend.","type":"noun","meaning_category":"日本経済新聞社"}]}