{"word":"vastiest","priority":"☆☆☆","meanings":[{"part_of_speech":"adjective","definition":"vastの最上級。非常に広大な、莫大な。","english_definition":"Superlative form of 'vast'; most extensive or immense.","examples":[{"sentence":"This is the vastiest desert I have ever seen.","translation":"これは私が見た中で最も広大な砂漠だ。"},{"sentence":"The vastiest ocean stretches before us.","translation":"私たちの目の前には、最も広大な海が広がっている。"}],"collocations":["vastiest desert","vastiest ocean","vastiest expanse"],"synonyms":["most immense","most extensive","most enormous","most boundless"],"antonyms":["smallest","least","tiniest"]},{"part_of_speech":"adjective","definition":"(古語)道徳的に、または精神的に最も広大な。","english_definition":"(Archaic) Most extensive in moral or spiritual sense.","examples":[{"sentence":"He possessed the vastiest understanding of human nature.","translation":"彼は人間性について最も広範な理解を持っていた。"}],"collocations":["vastiest understanding","vastiest wisdom"],"synonyms":["most profound","most comprehensive","most insightful"],"antonyms":["shallowest","least profound"]}],"etymology":{"value":"'Vast'に最上級語尾'-iest'が付いた形。","priority":"☆☆☆"},"pronunciation":{"ipa":"/ˈvæstiɪst/","syllables":"vas-ti-est"},"inflection":{"adjective_forms":{"comparative":"vaster","superlative":"vastiest"}},"usage_notes":{"explanation":"'Vastiest'は'vast'の最上級であり、非常にまれな単語です。通常は'most vast'という表現が用いられます。文学的な文脈や、古風な響きを意図する場合に使用されることがあります。","priority":"☆☆☆"},"common_mistakes":{"examples":[{"incorrect":"✗ The vastiest important thing is love.","correct":"✓ The most important thing is love.","note":"'Vastiest'は物理的な広がりや規模を表す場合に適しています。重要性を表す場合は'most important'を使用します。"}],"priority":"☆☆☆"},"related_words":{"derivatives":["vast","vastly","vastness"],"related_forms":["most vast"]},"level_frequency":{"CEFR":"N/A (非常にまれな単語)","frequency_google_ngram":"非常に低い","priority":"☆☆☆"},"readability_explanation":{"level":"C2","text":"'Vastiest'は'vast'の最上級であり、非常にまれな単語です。通常は'most vast'という表現が用いられます。文学的な文脈や、古風な響きを意図する場合に使用されることがあります。"},"example_sentences":[{"sentence":"The vastiest plains stretched out before the pioneers.","translation":"開拓者たちの目の前には、最も広大な平原が広がっていた。","type":"adjective","meaning_category":"広大な"},{"sentence":"It was the vastiest collection of knowledge ever assembled.","translation":"それは、これまでに集められた中で最も広大な知識の集積だった。","type":"adjective","meaning_category":"莫大な"}]}