{"word":"Upbreak","priority":"☆☆☆","meanings":[{"part_of_speech":"noun","definition":"(地質学) 地層の隆起または断裂","english_definition":"(geology) An uplift or disruption of strata.","examples":[{"sentence":"The upbreak in the rock formation revealed ancient fossils.","translation":"その岩層の隆起によって、古代の化石が明らかになった。"}],"collocations":[],"synonyms":["uplift","fault","fracture"],"antonyms":[]}],"etymology":{"value":"'Up-' (上へ) + 'break' (破壊、断裂) の組み合わせ。地層が上方向に破壊・隆起する様子を表す。","priority":"☆☆☆"},"pronunciation":{"ipa":"/ˈʌpˌbreɪk/","syllables":"up-break"},"inflection":{"noun_plural":"Upbreaks"},"usage_notes":{"explanation":"地質学の専門用語で、一般的には使われません。地層の隆起や断裂を指す場合に用いられます。","priority":"☆☆☆"},"common_mistakes":{},"related_words":{"derivatives":[],"phrasal_verbs":[]},"level_frequency":{"CEFR":"N/A","frequency_google_ngram":"非常に低頻度 (Very low frequency)","priority":"☆☆☆"},"readability_explanation":{"level":"C2","text":"'Upbreak' is a technical term used in geology to describe the uplift or disruption of rock layers. It is not commonly used in everyday language. Understanding this word requires knowledge of geological processes and terminology."},"example_sentences":[{"sentence":"The geologist studied the upbreak to understand the region's tectonic history.","translation":"地質学者は、その地域の構造史を理解するために、隆起を調査した。","type":"noun","meaning_category":"地質学"}]}