{"word":"beautiful-legged","priority":"N/A","meanings":[{"part_of_speech":"adjective","definition":"Having beautiful legs.","english_definition":"Possessing attractive or aesthetically pleasing legs.","examples":[{"sentence":"The dancer was known for being beautiful-legged.","translation":"そのダンサーは脚が美しいことで知られていた。"},{"sentence":"She was described as a beautiful-legged woman in the advertisement.","translation":"彼女は広告の中で脚が美しい女性として描かれていた。"}],"collocations":["beautiful-legged woman","beautiful-legged dancer","beautiful-legged model"],"synonyms":["shapely-legged","well-formed-legged","attractive-legged"],"antonyms":["ugly-legged","unattractive-legged"]}],"etymology":{"value":"Combination of 'beautiful' and 'legged'.","priority":"N/A"},"pronunciation":{"ipa":"/ˈbjuːtɪfʊl leɡd/","syllables":"beau-ti-ful-legged"},"inflection":{"notes":"Adjective; does not inflect."},"usage_notes":{"explanation":"This adjective is descriptive and subjective, often used to compliment or describe someone's physical appearance. Its usage can be considered objectifying depending on the context.","priority":"N/A"},"common_mistakes":{},"related_words":{"derivatives":[]},"level_frequency":{},"readability_explanation":{"level":"Intermediate","text":"This is a compound adjective formed by combining the adjective 'beautiful' with the past participle 'legged'. It describes someone who has beautiful legs. The word is relatively straightforward in meaning but not commonly used."},"example_sentences":[{"sentence":"The magazine featured a beautiful-legged model on its cover.","translation":"その雑誌の表紙には脚の美しいモデルが掲載されていた。","type":"adjective","meaning_category":"Physical appearance"},{"sentence":"He admired the beautiful-legged actress from afar.","translation":"彼は遠くから脚の美しい女優を称賛した。","type":"adjective","meaning_category":"Physical appearance"}]}