{"word":"sandarac","priority":"★☆☆","meanings":[{"part_of_speech":"noun","definition":"サンダラック（北アフリカ産のマツ科の樹木「Callitris quadrivalvis」またはその樹脂）","english_definition":"A brittle, faintly aromatic, translucent resin obtained from the small coniferous tree Callitris quadrivalvis (formerly Tetraclinis articulata) native to Northwest Africa.","examples":[{"sentence":"Sandarac was traditionally used in varnishes and incense.","translation":"サンダラックは伝統的にワニスや線香に使用されていた。"},{"sentence":"The cabinet was finished with sandarac varnish for protection.","translation":"そのキャビネットは保護のためにサンダラックワニスで仕上げられていた。"}],"collocations":["sandarac resin (サンダラック樹脂)","sandarac varnish (サンダラックワニス)","sandarac tree (サンダラックの木)"],"synonyms":["thuya gum","citron-tree resin"],"antonyms":[]},{"part_of_speech":"noun","definition":"（植物学）サンダラックノキ（Callitris属の樹木）","english_definition":"Any tree of the genus Callitris, especially Callitris quadrivalvis.","examples":[{"sentence":"The sandarac grows in the Atlas Mountains region.","translation":"サンダラックノキはアトラス山脈地域に生育する。"}],"collocations":[],"synonyms":["arar tree","citron-wood"],"antonyms":[]}],"etymology":{"value":"中世ラテン語「sandaracha」から、これは古代ギリシャ語「σανδαράκη (sandarákē)」に由来。元々は赤色の硫化ヒ素（雄黄）を指したが、後に樹脂の意味に転用された。アラビア語「sandarus」との関連も指摘される。","priority":"★☆☆"},"pronunciation":{"ipa":"/ˈsændəræk/","syllables":"san-da-rac"},"inflection":{"noun_plural":"sandaracs"},"usage_notes":{"explanation":"「**sandarac**」は専門的な語彙で、主に以下の文脈で使用されます：\n1. 伝統的なワニスや塗料の材料として（特に楽器や美術品の保護用）\n2. 植物学で北アフリカ原産の針葉樹を指す場合\n現代では合成樹脂に取って代わられたため、使用頻度は低いが、美術修復や伝統工芸の文脈で登場することがあります。「sandarac」と「sandarach」のスペル変種がありますが、前者がより一般的です。","priority":"★☆☆"},"common_mistakes":{"examples":[{"incorrect":"✗ The violin was coated with sandalac.","correct":"✓ The violin was coated with sandarac.","note":"「sandalac」は誤ったスペルです。正しくは「sandarac」です。"}],"priority":"★☆☆"},"related_words":{"derivatives":[],"idioms_phrases":[],"priority":"★☆☆"},"level_frequency":{"CEFR":"C2 (専門用語)","frequency_google_ngram":"極めて低頻度 (Very low frequency)","priority":"★☆☆"},"readability_explanation":{"level":"C2","text":"「**sandarac**」は非常に特殊な専門用語で、通常は美術材料学、植物学、または伝統工芸の文脈でしか登場しません。一般の英語学習者が遭遇する可能性は極めて低く、上級者向けの専門語彙です。"},"example_sentences":[{"sentence":"Ancient Egyptians used **sandarac** in mummification processes.","translation":"古代エジプト人はミイラ化の過程でサンダラックを使用した。","type":"noun","meaning_category":"樹脂"},{"sentence":"The **sandarac** varnish gives a warm amber tone to wood surfaces.","translation":"サンダラックワニスは木の表面に暖かい琥珀色のトーンを与える。","type":"noun","meaning_category":"樹脂"},{"sentence":"Botanists study the drought-resistant properties of the **sandarac** tree.","translation":"植物学者たちはサンダラックノキの耐旱性特性を研究している。","type":"noun","meaning_category":"植物"}]}