{"word":"redesertion","priority":"★☆☆","meanings":[{"part_of_speech":"noun","definition":"再遺棄、再放棄","english_definition":"The act of deserting again; a second or repeated act of desertion.","examples":[{"sentence":"The soldier was charged with redesertion after returning to his unit without permission.","translation":"その兵士は、許可なく部隊に戻った後、再遺棄の罪で告発された。"},{"sentence":"The redesertion of the project by the investors left the company in a difficult financial situation.","translation":"投資家によるプロジェクトの再放棄により、会社は困難な財政状況に陥った。"}],"collocations":["charge of redesertion","act of redesertion"],"synonyms":["reabandonment","second desertion","repeated abandonment"],"antonyms":["continued support","remaining","staying"]}],"etymology":{"value":"\"re-\" (again) + \"desertion\" (the act of deserting).","priority":"★★☆"},"pronunciation":{"ipa":"/ˌriːdɪˈzɜːrʃən/","syllables":"re-de-ser-tion"},"inflection":{"noun_plural":"redesertions"},"usage_notes":{"explanation":"\"Redesertion\" refers to the act of deserting or abandoning something or someone a second time or repeatedly. It often implies a breach of trust or commitment. It is a relatively rare word, typically used in formal or legal contexts.","priority":"★★☆"},"common_mistakes":{"examples":[{"incorrect":"✗ The redesertion was a surprise because he never deserted before.","correct":"✓ The desertion was a surprise because he never deserted before.","note":"If it's the first instance of desertion, use \"desertion,\" not \"redesertion.\""}],"priority":"★★☆"},"related_words":{"derivatives":["desert (verb, noun)","deserter (noun)","desertion (noun)"],"priority":"★★☆"},"level_frequency":{"frequency_google_ngram":"Low frequency","priority":"★☆☆"},"readability_explanation":{"level":"C1","text":"\"Redesertion\" is a formal and relatively rare word. It is formed by adding the prefix \"re-\" to \"desertion,\" indicating a repeated act of deserting or abandoning. It is most likely to be encountered in legal or military contexts when discussing repeated instances of abandonment or unauthorized absence."},"example_sentences":[{"sentence":"His redesertion of his post led to severe consequences.","translation":"彼の持ち場からの再遺棄は深刻な結果をもたらした。","type":"general"},{"sentence":"The company faced redesertion by key personnel after the merger.","translation":"合併後、会社は主要な人材による再放棄に直面した。","type":"business"},{"sentence":"The legal documents detailed the charges of redesertion against the accused.","translation":"法律文書は、被告に対する再遺棄の罪の詳細を記述していた。","type":"legal"}]}