{"word":"Unhomelikeness","priority":"★☆☆","meanings":[{"part_of_speech":"noun","definition":"居心地の悪さ、家庭的でないこと、くつろげなさ","english_definition":"The state or quality of not being homelike; a lack of comfort, coziness, or familiarity.","examples":[{"sentence":"The unhomelikeness of the hotel room made it difficult to relax.","translation":"そのホテルの部屋の居心地の悪さが、リラックスすることを難しくした。"},{"sentence":"She felt a sense of unhomelikeness in the unfamiliar city.","translation":"彼女は見知らぬ街で、くつろげない感じを覚えた。"},{"sentence":"The stark, modern design contributed to the unhomelikeness of the space.","translation":"殺風景でモダンなデザインが、その空間の家庭的でない雰囲気を助長した。"}],"collocations":["sense of unhomelikeness (居心地の悪さ)","feeling of unhomelikeness (くつろげなさ)","contribute to unhomelikeness (居心地の悪さを助長する)"],"synonyms":["uncomfortableness","unfamiliarity","alienation","discomfort","inhospitality","coldness","sterility"],"antonyms":["homeliness","comfort","coziness","familiarity","hospitality","warmth"]},{"part_of_speech":"noun","definition":"家庭的な要素の欠如、家庭らしさのなさ","english_definition":"The absence of qualities associated with a home, such as warmth, comfort, and personal touches.","examples":[{"sentence":"The unhomelikeness of the apartment was apparent in its bare walls and lack of personal items.","translation":"そのアパートの家庭的でない雰囲気は、むき出しの壁と個人的な物の欠如に明らかだった。"},{"sentence":"They tried to combat the unhomelikeness by adding plants and colorful decorations.","translation":"彼らは植物やカラフルな装飾を加えることで、家庭らしさのなさを解消しようとした。"}],"collocations":["lack of homeliness (家庭らしさの欠如)","absence of comfort (快適さの欠如)","combat unhomelikeness (家庭らしさのなさを解消する)"],"synonyms":["lack of warmth","absence of comfort","sterility","impersonality","bareness"],"antonyms":["homeliness","warmth","comfort","personalization"]}],"etymology":{"value":"\"Unhomelikeness\"は、接頭辞 \"un-\"（否定）、\"homelike\"（家庭的な）、および接尾辞 \"-ness\"（状態や性質を示す）から構成されています。\"Homelike\" は、\"home\"（家）と \"-like\"（～のような）を組み合わせたものです。したがって、文字通りには「家庭的でない状態」または「家庭的でない性質」を意味します。","priority":"★☆☆"},"pronunciation":{"ipa":"/ʌnˈhoʊmlaɪknəs/","syllables":"un-home-like-ness"},"inflection":{"noun_plural":"unhomelikenesses (まれに複数形で使用される)"},"usage_notes":{"explanation":"\"Unhomelikeness\"は、フォーマルな文脈や文学的な表現で用いられることが多く、日常会話ではあまり一般的ではありません。より一般的な表現としては、\"uncomfortable atmosphere\"（居心地の悪い雰囲気）、\"lack of coziness\"（くつろぎの欠如）、\"unfamiliar environment\"（慣れない環境）などが挙げられます。","priority":"★☆☆"},"common_mistakes":{"examples":[{"incorrect":"✗ The room had a very unhomelikeness.","correct":"✓ The room had a strong sense of unhomelikeness.","note":"\"Unhomelikeness\"は不可算名詞として扱われるため、不定冠詞 \"a\" は通常使用しません。代わりに、\"sense of unhomelikeness\"（居心地の悪さ）のような表現を用います。"},{"incorrect":"✗ I felt unhomelikeness in my new school.","correct":"✓ I felt a sense of unhomelikeness in my new school. / ✓ I felt unhomelike in my new school.","note":"\"Unhomelikeness\"は名詞であり、感情の対象を指します。感情自体を表す場合は、\"I felt unhomelike\"（形容詞）または \"I felt a sense of unhomelikeness\"（名詞句）を使用します。"}],"priority":"★☆☆"},"related_words":{"derivatives":["unhomelike (形容詞: 家庭的でない)","homelike (形容詞: 家庭的な)","homeliness (名詞: 家庭的な雰囲気、居心地の良さ)"],"antonyms":["homeliness (名詞: 家庭的な雰囲気、居心地の良さ)","comfort (名詞: 快適さ)","familiarity (名詞: 親しみやすさ)"],"related_concepts":["alienation (疎外感)","discomfort (不快感)","sterility (殺風景さ)","impersonality (無個性さ)"]},"level_frequency":{"CEFR":"N/A (非常にまれな単語)","frequency_google_ngram":"非常に低頻度 (Very low frequency) - 日常的な使用はまれ。","priority":"★☆☆"},"readability_explanation":{"level":"C2","text":"\"Unhomelikeness\"は、高度な語彙力を持つ読者層を対象とした、抽象的な概念を表現する際に用いられる専門的な単語です。日常会話や一般的な文章ではほとんど使用されず、文学作品や学術論文など、特定の文脈でのみ見られます。この単語は、家庭的な温かさや快適さ、親しみやすさといった要素が欠如している状態を指し、感情的な疎外感や不快感を伴うことが多いです。読解においては、文脈から意味を推測する能力が求められます。"},"example_sentences":[{"sentence":"The hospital, with its cold, sterile environment, exuded an air of utter unhomelikeness.","translation":"病院は、冷たく殺風景な環境で、完全に家庭的でない雰囲気を醸し出していた。","type":"noun","meaning_category":"居心地の悪さ"},{"sentence":"The traveler noted the unhomelikeness of the temporary lodgings, longing for the familiar comforts of home.","translation":"旅行者は、一時的な宿泊施設の居心地の悪さに気づき、慣れ親しんだ家の快適さを恋しがった。","type":"noun","meaning_category":"くつろげなさ"},{"sentence":"The artist sought to capture the unhomelikeness of urban spaces in their stark and unsettling paintings.","translation":"そのアーティストは、殺風景で不安を煽る絵画で、都市空間の家庭的でない雰囲気を捉えようとした。","type":"noun","meaning_category":"家庭的な要素の欠如"}]}