{"word":"descontado","priority":"N/A","meanings":[{"part_of_speech":"adjective","definition":"割引された、割り引かれた","english_definition":"discounted","examples":[{"sentence":"El precio descontado es de 10 euros.","translation":"The discounted price is 10 euros.","note":"This is a simple example."}],"collocations":["precio descontado","valor descontado"],"synonyms":["rebajado","reducido"],"antonyms":["aumentado","incrementado"]},{"part_of_speech":"verb","definition":"動詞descontarの過去分詞","english_definition":"past participle of the verb 'descontar' (to discount, to deduct)","examples":[{"sentence":"El dinero fue descontado de su cuenta.","translation":"The money was deducted from his account.","note":"This is a simple example."}],"collocations":["ser descontado","haber descontado"],"synonyms":["deducido","restado"],"antonyms":["sumado","agregado"]}],"etymology":{"value":"From the verb 'descontar', which comes from 'des-' (prefix indicating negation or separation) and 'contar' (to count).","note":"This is the etymology of the verb from which the adjective is derived."},"pronunciation":{"ipa":"/des.konˈta.ðo/","note":"This is a phonetic transcription."},"inflection":{"forms":["masculine singular: descontado","feminine singular: descontada","masculine plural: descontados","feminine plural: descontadas"],"note":"This shows the different forms the adjective can take."},"usage_notes":{"explanation":"'Descontado' is used to describe something that has had a discount applied to it. It can also be used as the past participle of the verb 'descontar', meaning 'deducted' or 'discounted'. The meaning is usually clear from the context.","note":"This explains how the word is used."},"common_mistakes":{"examples":[{"incorrect":"El precio es descuento.","correct":"El precio es descontado.","note":"'Descuento' is a noun (discount), while 'descontado' is an adjective (discounted)."}],"note":"This shows a common mistake in usage."},"related_words":{"derivatives":["descontar (verb): to discount, to deduct","descuento (noun): discount"],"note":"These are related words."},"level_frequency":{"level":"B1","note":"This is an estimated level."},"readability_explanation":{"text":"'Descontado' is a relatively common word used in commercial contexts to describe prices that have been reduced. It is derived from the verb 'descontar' and is used as an adjective or a past participle. Understanding the verb 'descontar' helps to understand the meaning of 'descontado'.","note":"This provides a simple explanation."},"example_sentences":[{"sentence":"Los billetes descontados no son reembolsables.","translation":"Discounted tickets are non-refundable.","type":"adjective","meaning_category":"discounted"},{"sentence":"El impuesto fue descontado del salario.","translation":"The tax was deducted from the salary.","type":"past participle","meaning_category":"deducted"}]}