{"word":"mencatat","priority":"★★★","meanings":[{"part_of_speech":"verb","transitivity":"vt","definition":"記録する、書き留める、メモする","english_definition":"to record, write down, take notes of","examples":[{"sentence":"Guru itu mencatat nama-nama siswa yang tidak hadir.","translation":"先生は欠席した生徒の名前を記録しました。"}],"collocations":["mencatat data (データを記録する)","mencatat hasil (結果を記録する)","mencatat nama (名前を記録する)","mencatat nomor (番号を記録する)","mencatat pengeluaran (支出を記録する)","mencatat kejadian (出来事を記録する)"],"synonyms":["menulis","merekan","membukukan","menginventarisasi"],"antonyms":["melupakan","menghilangkan"]},{"part_of_speech":"verb","transitivity":"vt","definition":"注意する、留意する","english_definition":"to note, pay attention to","examples":[{"sentence":"Mencatat hal ini penting untuk keberhasilan proyek.","translation":"プロジェクトの成功のためには、このことに留意することが重要です。"}],"collocations":["mencatat hal penting (重要なことに注意する)","mencatat perubahan (変化に注意する)","mencatat perbedaan (違いに注意する)"],"synonyms":["memperhatikan","mempertimbangkan","mengingat","menyadari"],"antonyms":["mengabaikan","menyepelekan"]}],"etymology":{"value":"語源は「catat」であり、それは「書き留める」という意味を持つ。接頭辞「me-」が付くことで、動詞化している。","priority":"★★☆"},"pronunciation":{"ipa":"/mənˈt͡ʃatat/","syllables":"men-ca-tat"},"inflection":{"verb_forms":{"present":"mencatat","past":"mencatat","future":"akan mencatat","imperative":"catatlah"}},"usage_notes":{"explanation":"「mencatat」は、何かを記録したり、書き留めたり、メモしたりする行為を指します。また、特定の情報や事実を認識し、注意を払うという意味合いも持ちます。文脈によって意味が異なるため、注意が必要です。","priority":"★★★"},"common_mistakes":{"examples":[{"incorrect":"Saya catat buku itu.","correct":"Saya mencatat isi buku itu.","note":"「catat」は名詞を直接目的語にすることが少ないため、「mencatat」を使って内容を記録することを明確にする必要があります。"},{"incorrect":"Dia mencatat lupa.","correct":"Dia lupa mencatat.","note":"動詞の順序が逆です。「lupa mencatat」は「記録することを忘れた」という意味になります。"}],"priority":"★★☆"},"related_words":{"derivatives":["catatan (名詞: ノート、記録、メモ)","pencatatan (名詞: 記録行為、記録プロセス)","tercatat (形容詞: 記録された、登録された)"],"priority":"★★★"},"level_frequency":{"frequency_google_ngram":"高頻度","CEFR":"B1","priority":"★☆☆"},"readability_explanation":{"level":"B1","text":"「mencatat」は、何かを書き留める、記録するという意味の動詞です。授業で先生の話をメモしたり、会議で議事録を取ったり、日記をつけたりする時に使います。また、何か重要なことに気づいて、それを覚えておく、注意するという意味でも使われます。例えば、「mencatat bahwa...（～ということを記録する/注意する）」のように使います。"},"example_sentences":[{"sentence":"Sekretaris itu mencatat semua poin penting dalam rapat.","translation":"秘書は会議のすべての重要なポイントを記録しました。","type":"general","meaning_category":"記録する"},{"sentence":"Jangan lupa mencatat tanggal kadaluarsa produk.","translation":"製品の有効期限を記録することを忘れないでください。","type":"general","meaning_category":"記録する"},{"sentence":"Penting untuk mencatat setiap perubahan dalam proyek ini.","translation":"このプロジェクトのすべての変更を記録することが重要です。","type":"general","meaning_category":"注意する"}]}