{"word":"Brecksville","priority":"☆☆☆","meanings":[{"part_of_speech":"noun","definition":"ブレックスビル：アメリカ合衆国オハイオ州の都市","english_definition":"A city in Cuyahoga County, Ohio, United States.","examples":[{"sentence":"Brecksville is a suburb of Cleveland.","translation":"ブレックスビルはクリーブランドの郊外都市です。"}],"collocations":[],"synonyms":[],"antonyms":[]}],"etymology":{"value":"ブレックスビルの名前は、この地域を最初に調査したジョン・ブレックに由来します。","priority":"★★☆"},"pronunciation":{"ipa":"/ˈbrɛksvɪl/","syllables":"Brecks-ville"},"inflection":{},"usage_notes":{},"common_mistakes":{},"related_words":{},"level_frequency":{},"readability_explanation":{},"example_sentences":[]}