{"word":"Provo","priority":"★★☆","meanings":[{"part_of_speech":"noun","definition":"プロボ：アメリカ合衆国ユタ州にある都市。ブリガムヤング大学が所在する。","english_definition":"A city in Utah, United States. It is home to Brigham Young University.","examples":[{"sentence":"Provo is located south of Salt Lake City.","translation":"プロボはソルトレイクシティの南に位置しています。"},{"sentence":"Brigham Young University is a major employer in Provo.","translation":"ブリガムヤング大学はプロボの主要な雇用主です。"}],"collocations":["Provo Utah","Brigham Young University Provo","Provo River"],"synonyms":[],"antonyms":[]}],"etymology":{"value":"プロボという名前は、フランス系カナダ人の毛皮商人エティエンヌ・プロヴォスト（Étienne Provost）に由来する。","priority":"★★★"},"pronunciation":{"ipa":"/ˈproʊvoʊ/","syllables":"Pro-vo"},"inflection":{},"usage_notes":{"explanation":"Provoは固有名詞であり、通常は地名としてのみ使用されます。文法的な特別な注意点はありません。","priority":"★★★"},"common_mistakes":{},"related_words":{"derivatives":["Provoite (プロボの住民)"],"related_places":["Salt Lake City","Utah"],"related_people":["Étienne Provost"]},"level_frequency":{"frequency_google_ngram":"比較的低頻度 (Relatively low frequency) - 地名のため、一般的な語彙に比べると頻度は低い。","priority":"★★☆"},"readability_explanation":{"level":"B1","text":"Provo is the name of a city. It's not a word you'll use very often unless you're talking about Utah or Brigham Young University.","priority":"★★★"},"example_sentences":[{"sentence":"I'm visiting Provo next week for a conference.","translation":"来週、会議でプロボを訪れます。","type":"noun","meaning_category":"地名"},{"sentence":"She went to Brigham Young University in Provo.","translation":"彼女はプロボにあるブリガムヤング大学に通っていました。","type":"noun","meaning_category":"地名"}]}