{"word":"high-purity","priority":"★★☆","meanings":[{"part_of_speech":"adjective","definition":"高純度の","english_definition":"having a high degree of purity; containing very few impurities.","examples":[{"sentence":"High-purity silicon is essential for manufacturing semiconductors.","translation":"高純度のシリコンは半導体製造に不可欠です。"},{"sentence":"This high-purity metal is used in aerospace applications.","translation":"この高純度の金属は航空宇宙用途で使用されています。"},{"sentence":"The company specializes in producing high-purity chemicals.","translation":"その会社は高純度化学製品の製造を専門としています。"}],"collocations":["high-purity water (高純度水)","high-purity gas (高純度ガス)","high-purity material (高純度材料)","high-purity silicon (高純度シリコン)","high-purity chemical (高純度化学物質)"],"synonyms":["ultrapure","refined","purified","high-grade"],"antonyms":["impure","contaminated","low-purity","unrefined"]}],"etymology":{"value":"\"high\" (高い) + \"purity\" (純度) の複合語。材料や物質の純度が高いことを示すために使われる。","priority":"★★☆"},"pronunciation":{"ipa":"/ˌhaɪ ˈpjʊərəti/","syllables":"high-pu-ri-ty"},"inflection":{"notes":"形容詞なので、比較級・最上級の変化はありません。"},"usage_notes":{"explanation":"\"**high-purity**\" は、特定の物質や材料が非常に高い純度を持っていることを示すために使用される形容詞です。科学、工業、技術分野でよく用いられ、不純物が非常に少ない状態を指します。半導体製造、医薬品、特殊化学製品など、高い品質と性能が求められる用途で特に重要です。数値で純度を示す場合もあります（例：99.999% pure）。","priority":"★★★"},"common_mistakes":{"examples":[{"incorrect":"✗ high purity material","correct":"✓ high-purity material","note":"複合形容詞として使用する場合、通常はハイフンで繋ぎます。"},{"incorrect":"✗ a material with high purity","correct":"✓ a high-purity material","note":"\"high-purity\" は形容詞として名詞を修飾します。"}],"priority":"★★☆"},"related_words":{"derivatives":["purity (名詞: 純度)","purify (動詞: 精製する)","pure (形容詞: 純粋な)"],"related_terms":["ultra-high purity (超高純度)","trace impurities (微量不純物)","semiconductor grade (半導体グレード)","pharmaceutical grade (医薬品グレード)"],"priority":"★★☆"},"level_frequency":{"CEFR":"C1","frequency_google_ngram":"中頻度 (Moderate frequency) - 特定の専門分野でよく使われる語彙。","priority":"★☆☆"},"readability_explanation":{"level":"C1","text":"「**high-purity**」は、ある物質が非常にきれいであることを意味する言葉です。科学や工業の分野でよく使われ、不純物がほとんどない状態を表します。例えば、半導体を作るためには「**high-purity** silicon（高純度シリコン）」が必要です。この言葉は、高い品質や性能が求められる場合に重要な意味を持ちます。"},"example_sentences":[{"sentence":"The experiment requires **high-purity** nitrogen gas.","translation":"その実験には高純度の窒素ガスが必要です。","type":"adjective","meaning_category":"高純度"},{"sentence":"They developed a new method for producing **high-purity** water.","translation":"彼らは高純度の水を製造するための新しい方法を開発しました。","type":"adjective","meaning_category":"高純度"},{"sentence":"The **high-purity** sample was analyzed using mass spectrometry.","translation":"高純度のサンプルは質量分析法を用いて分析されました。","type":"adjective","meaning_category":"高純度"}]}