{"word":"pallar","priority":"☆☆☆","meanings":[{"part_of_speech":"noun","definition":"(歴史)祭壇を覆う布、祭壇布","english_definition":"(historical) A cloth covering for an altar; an altar cloth.","examples":[{"sentence":"The pallar was embroidered with gold thread.","translation":"祭壇布は金の糸で刺繍されていた。"}],"collocations":[],"synonyms":["altar cloth","veil"],"antonyms":[]},{"part_of_speech":"noun","definition":"(紋章学)Y字型の紋章","english_definition":"(heraldry) An ordinary consisting of a Y-shaped figure, usually having its arms in the chief and its foot in the base of the shield.","examples":[{"sentence":"The coat of arms featured a pallar in the center.","translation":"紋章の中央にはY字型の紋章が描かれていた。"}],"collocations":[],"synonyms":[],"antonyms":[]}],"etymology":{"value":"ラテン語の「pallium」（外套、覆い）に由来する。","priority":"★★☆"},"pronunciation":{"ipa":"/ˈpælər/","syllables":"pal-lar"},"inflection":{"noun_plural":"pallars"},"usage_notes":{"explanation":"「pallar」は、あまり一般的な単語ではありません。主に歴史的な文脈や紋章学で使用されます。現代英語では、祭壇布を指す場合は「altar cloth」の方が一般的です。","priority":"★★☆"},"common_mistakes":{"examples":[],"priority":"☆☆☆"},"related_words":{"derivatives":["pallium"],"phrasal_verbs":[]},"level_frequency":{"CEFR":"N/A","frequency_google_ngram":"非常に低頻度","priority":"☆☆☆"},"readability_explanation":{"level":"C2","text":"「pallar」は専門用語であり、一般的な語彙ではありません。歴史や紋章学に関わる文脈でのみ使用される可能性が高いです。"},"example_sentences":[{"sentence":"The priest carefully arranged the pallar on the altar.","translation":"司祭は祭壇の上に祭壇布を丁寧に配置した。","type":"noun","meaning_category":"祭壇布"},{"sentence":"The arms of the diocese include a blue pallar.","translation":"その教区の紋章には青いY字型の紋章が含まれている。","type":"noun","meaning_category":"紋章"}]}