{"word":"Waco","priority":"N/A","meanings":[{"part_of_speech":"noun","definition":"ウェーコ：アメリカ合衆国テキサス州中央部に位置する都市。","english_definition":"A city in central Texas, United States.","examples":[{"sentence":"Waco is located on the Brazos River.","translation":"ウェーコはブラゾス川沿いに位置しています。"},{"sentence":"The Branch Davidian compound was located near Waco.","translation":"ブランチ・ダビディアンの施設はウェーコ近郊にありました。"}],"collocations":[],"synonyms":[],"antonyms":[]}],"etymology":{"value":"由来は不明だが、ウェーコ族（Waco tribe）というアメリカ先住民にちなんで名付けられたとされる。","priority":"★★☆"},"pronunciation":{"ipa":"/ˈweɪkoʊ/","syllables":"Way-co"},"inflection":{},"usage_notes":{"explanation":"ウェーコは、1993年のブランチ・ダビディアン集団と連邦政府との間の武力衝突（ウェーコ事件）の舞台となったことで知られています。","priority":"★★☆"},"common_mistakes":{},"related_words":{"derivatives":[],"related_terms":["Texas","Branch Davidians","Mount Carmel Center"],"priority":"★★☆"},"level_frequency":{},"readability_explanation":{"level":"N/A","text":"固有名詞のため、読みやすさの説明は不要です。"},"example_sentences":[{"sentence":"I'm planning a trip to Waco, Texas.","translation":"テキサス州のウェーコへの旅行を計画しています。","type":"noun","meaning_category":"都市"},{"sentence":"The Waco siege was a tragic event in American history.","translation":"ウェーコ包囲戦はアメリカの歴史における悲劇的な出来事でした。","type":"noun","meaning_category":"都市"}]}